PyCar/__init__.py
car/__init__.py
PyCar-1.0.0.dist-info/METADATA
PyCar-1.0.0.dist-info/WHEEL
PyCar-1.0.0.dist-info/top_level.txt
PyCar-1.0.0.dist-info/RECORD
