Metadata-Version: 2.1
Name: PyCar
Version: 1.0.0
Summary: Vroom
